cjk_commons/__about__.py
cjk_commons/__init__.py
cjk_commons/file.py
cjk_commons/logging_.py
cjk_commons/settings.py
cjk_commons/zip.py
tests/__init__.py
tests/test_commons.py
cjk_commons-3.7.5.dist-info/METADATA
cjk_commons-3.7.5.dist-info/WHEEL
cjk_commons-3.7.5.dist-info/top_level.txt
cjk_commons-3.7.5.dist-info/RECORD
