Metadata-Version: 2.4
Name: cjk-commons
Version: 3.7.5
Summary: Commons
Author-email: Cujoko <cujoko@gmail.com>
License: MIT
Project-URL: repository, https://github.com/Cujoko-Dev/commons
Keywords: commons
Classifier: Development Status :: 5 - Production/Stable
Classifier: Intended Audience :: Developers
Classifier: License :: OSI Approved :: MIT License
Classifier: Natural Language :: Russian
Classifier: Programming Language :: Python :: 3.14
Classifier: Programming Language :: Python :: 3.13
Classifier: Programming Language :: Python :: 3.12
Classifier: Programming Language :: Python :: 3.11
Classifier: Programming Language :: Python :: 3.10
Classifier: Topic :: Software Development
Classifier: Topic :: Utilities
Requires-Python: >=3.10
Requires-Dist: appdirs>=1.4.4
Requires-Dist: loguru>=0.6.0
Requires-Dist: pyyaml>=6.0
Requires-Dist: yodl>=1.0.0
